requests_header_refresh/__init__.py
requests_header_refresh/requests_header_refresh.py
requests_header_refresh-1.0.5.dist-info/METADATA
requests_header_refresh-1.0.5.dist-info/WHEEL
requests_header_refresh-1.0.5.dist-info/licenses/LICENSE
requests_header_refresh-1.0.5.dist-info/RECORD
