Metadata-Version: 2.1
Name: requests_header_refresh
Version: 1.0.5
Summary: Adds support for the Refresh header in requests. Check out the README for more info.
Project-URL: Homepage, https://github.com/matthew-hajec/requests_header_refresh
Project-URL: Issues, https://github.com/matthew-hajec/requests_header_refresh/issues
Author-email: mhajec21 <matthew.hajec02@gmail.com>
License-File: LICENSE
Classifier: License :: OSI Approved :: MIT License
Classifier: Operating System :: OS Independent
Classifier: Programming Language :: Python :: 3
Requires-Python: >=3.7
Requires-Dist: requests
